commands/__init__.py
commands/build.py
commands/cli.py
commands/create.py
commands/dev.py
commands/_templates/reactjs/index.html
commands/_templates/reactjs/src/App.jsx
commands/_templates/reactjs/src/index.css
commands/_templates/reactjs/src/main.jsx
commands/_templates/reactts/index.html
commands/_templates/reactts/src/App.tsx
commands/_templates/reactts/src/index.css
commands/_templates/reactts/src/main.tsx
utils/__init__.py
utils/esbuild.py
utils/server.py
utils/tailwind.py
utils/watcher.py
pypackx-1.0.2.dist-info/METADATA
pypackx-1.0.2.dist-info/WHEEL
pypackx-1.0.2.dist-info/entry_points.txt
pypackx-1.0.2.dist-info/top_level.txt
pypackx-1.0.2.dist-info/RECORD
