Metadata-Version: 2.4
Name: pypackx
Version: 1.0.2
Summary: React + Tailwind Dev-Server, Hot-live-Reloader and Production-Bundler (Rohit C.)
Author: Rohit Chauhan
License: MIT
Requires-Python: >=3.9
Requires-Dist: aiohttp>=3.9
Requires-Dist: watchfiles>=0.21
